emec_api/__init__.py
emec_api/__main__.py
emec_api/__version__.py
emec_api/api/__init__.py
emec_api/api/client.py
emec_api/api/utils.py
emec_api/application.py
emec_api/commands/__init__.py
emec_api/commands/about.py
emec_api/commands/scraper.py
emec_api-0.1.10.dist-info/LICENSE
emec_api-0.1.10.dist-info/METADATA
emec_api-0.1.10.dist-info/WHEEL
emec_api-0.1.10.dist-info/entry_points.txt
emec_api-0.1.10.dist-info/RECORD
