Metadata-Version: 2.1
Name: emec-api
Version: 0.1.10
Summary: API Python para obter informações de instituições de ensino superior.
Home-page: https://github.com/pavanad/emec-api
License: MIT
Keywords: universidades,cursos,e-mec,api,brasil
Author: Adilson Pavan
Author-email: adilson.pavan@gmail.com
Requires-Python: >=3.9,<4.0
Classifier: License :: OSI Approved :: MIT License
Classifier: Programming Language :: Python :: 3
Classifier: Programming Language :: Python :: 3.9
Classifier: Programming Language :: Python :: 3.10
Classifier: Programming Language :: Python :: 3.11
Classifier: Programming Language :: Python :: 3.12
Requires-Dist: aiohttp (>=3.8.1,<4.0.0)
Requires-Dist: beautifulsoup4 (>=4.10.0,<5.0.0)
Requires-Dist: cleo (>=0.8.1,<0.9.0)
Requires-Dist: numpy (==1.26.4)
Requires-Dist: pandas (>=1.4.2,<2.0.0)
Requires-Dist: pyfiglet (>=0.8.post1,<0.9)
Requires-Dist: tqdm (>=4.66.1,<5.0.0)
Project-URL: Repository, https://github.com/pavanad/emec-api
